mcp_server_starrocks/__init__.py
mcp_server_starrocks/connection_health_checker.py
mcp_server_starrocks/db_client.py
mcp_server_starrocks/db_summary_manager.py
mcp_server_starrocks/server.py
mcp_server_starrocks-0.2.0.dist-info/METADATA
mcp_server_starrocks-0.2.0.dist-info/WHEEL
mcp_server_starrocks-0.2.0.dist-info/entry_points.txt
mcp_server_starrocks-0.2.0.dist-info/licenses/LICENSE
mcp_server_starrocks-0.2.0.dist-info/RECORD
