Metadata-Version: 2.4
Name: mcp-server-starrocks
Version: 0.2.0
Summary: official MCP server for StarRocks
Project-URL: Home, https://github.com/starrocks/mcp-server-starrocks
Author-email: changbinglin <changbinglin@starrocks.com>
License: Apache-2.0
License-File: LICENSE
Requires-Python: >=3.10
Requires-Dist: adbc-driver-flightsql>=0.8.0
Requires-Dist: adbc-driver-manager>=0.8.0
Requires-Dist: fastmcp<2.13.0,>=2.12.0
Requires-Dist: kaleido==0.2.1
Requires-Dist: loguru>=0.7.3
Requires-Dist: mysql-connector-python>=9.2.0
Requires-Dist: pandas>=2.2.3
Requires-Dist: plotly>=6.0.1
Requires-Dist: pyarrow>=14.0.0
Provides-Extra: test
Requires-Dist: pytest-cov>=4.0.0; extra == 'test'
Requires-Dist: pytest>=7.0.0; extra == 'test'
